streamlit_cookie_banner/__init__.py
streamlit_cookie_banner/frontend/public/index.html
streamlit_cookie_banner/frontend/public/main.js
streamlit_cookie_banner/frontend/public/streamlit-component-lib.js
streamlit_cookie_banner/frontend/public/style.css
streamlit_cookie_banner-0.1.0.dist-info/LICENSE
streamlit_cookie_banner-0.1.0.dist-info/METADATA
streamlit_cookie_banner-0.1.0.dist-info/WHEEL
streamlit_cookie_banner-0.1.0.dist-info/top_level.txt
streamlit_cookie_banner-0.1.0.dist-info/RECORD
