Metadata-Version: 2.1
Name: streamlit-cookie-banner
Version: 0.1.0
Summary: A custom Streamlit component to display a basic cookie banner
Home-page: https://github.com/bowespublishing/streamlit-cookie-banner
Author: Luke Bowes
Author-email: luke.bowes@example.com
Classifier: Programming Language :: Python :: 3
Classifier: License :: OSI Approved :: MIT License
Classifier: Operating System :: OS Independent
Requires-Python: >=3.6
License-File: LICENSE
Requires-Dist: streamlit >=1.0
